mst/sql/__init__.py
mst/sql/sql.py
mst_sql-1.8.0.dist-info/METADATA
mst_sql-1.8.0.dist-info/WHEEL
mst_sql-1.8.0.dist-info/top_level.txt
mst_sql-1.8.0.dist-info/RECORD
