Metadata-Version: 2.1
Name: mst-sql
Version: 1.8.0
Summary: Utilities for interacting with S&T databases.
Author-email: Missouri University of Science and Technology - Information Technology <it-ai@mst.edu>
Requires-Python: >=3.8
Requires-Dist: mst-core
Requires-Dist: mst-authsrv
Requires-Dist: sqlalchemy
Requires-Dist: pymysql
